ibex_1d.py
ibex_1d-1.3.2.dist-info/LICENSE.txt
ibex_1d-1.3.2.dist-info/METADATA
ibex_1d-1.3.2.dist-info/WHEEL
ibex_1d-1.3.2.dist-info/entry_points.txt
ibex_1d-1.3.2.dist-info/top_level.txt
ibex_1d-1.3.2.dist-info/RECORD
