Metadata-Version: 2.1
Name: ibex-1d
Version: 1.3.2
Summary: Image 1D Barcode EXtractor - Detect and Extract 1D Barcode(s) in Photographs
Author-email: Ben Souchet <contact@bensouchet.dev>
Maintainer-email: Ben Souchet <contact@bensouchet.dev>
License: MIT License
Project-URL: Repository, https://github.com/BenSouchet/ibex_1d
Project-URL: Bug Tracker, https://github.com/BenSouchet/ibex_1d/issues
Keywords: opencv,computer-vision,barcode,detection,extraction,roi,image-recognition
Classifier: Development Status :: 5 - Production/Stable
Classifier: Intended Audience :: Developers
Classifier: Topic :: Scientific/Engineering :: Image Recognition
Classifier: License :: OSI Approved :: MIT License
Classifier: Programming Language :: Python :: 3.7
Classifier: Programming Language :: Python :: 3.8
Classifier: Programming Language :: Python :: 3.9
Classifier: Programming Language :: Python :: 3.10
Classifier: Programming Language :: Python :: 3.11
Classifier: Programming Language :: Python :: 3 :: Only
Requires-Python: >=3.7
License-File: LICENSE.txt
Requires-Dist: numpy
Requires-Dist: opencv-python
